[{"world":"palpagos","x":-722610,"y":-431080,"time":"both","level":50},{"world":"palpagos","x":-24316,"y":72068,"time":"both","level":30},{"world":"palpagos","x":-21782,"y":64843,"time":"both","level":30},{"world":"palpagos","x":-21722,"y":93659,"time":"both","level":30},{"world":"palpagos","x":-21353,"y":79562,"time":"both","level":30},{"world":"palpagos","x":-20938,"y":83927,"time":"both","level":30},{"world":"palpagos","x":-20147,"y":68331,"time":"both","level":30},{"world":"palpagos","x":-18567,"y":99035,"time":"both","level":30},{"world":"palpagos","x":-17259,"y":74788,"time":"both","level":30},{"world":"palpagos","x":-16171,"y":77578,"time":"both","level":30},{"world":"palpagos","x":-12397,"y":95537,"time":"both","level":30},{"world":"palpagos","x":-11614,"y":75890,"time":"both","level":30},{"world":"palpagos","x":-10650,"y":90536,"time":"both","level":30},{"world":"palpagos","x":-6752,"y":75263,"time":"both","level":30},{"world":"palpagos","x":-6008,"y":92616,"time":"both","level":30},{"world":"palpagos","x":-5812,"y":104394,"time":"both","level":30},{"world":"palpagos","x":-3210,"y":60697,"time":"both","level":30},{"world":"palpagos","x":-1612,"y":95841,"time":"both","level":30},{"world":"palpagos","x":-1551,"y":105565,"time":"both","level":30},{"world":"palpagos","x":-1036,"y":84631,"time":"both","level":30},{"world":"palpagos","x":-535,"y":116175,"time":"both","level":30},{"world":"palpagos","x":-113,"y":67829,"time":"both","level":30},{"world":"palpagos","x":627,"y":89241,"time":"both","level":30},{"world":"palpagos","x":1230,"y":72374,"time":"both","level":30},{"world":"palpagos","x":1953,"y":102000,"time":"both","level":30},{"world":"palpagos","x":2317,"y":95509,"time":"both","level":30},{"world":"palpagos","x":5259,"y":120774,"time":"both","level":30},{"world":"palpagos","x":5333,"y":128376,"time":"both","level":30},{"world":"palpagos","x":6348,"y":112835,"time":"both","level":30},{"world":"palpagos","x":6841,"y":85197,"time":"both","level":30},{"world":"palpagos","x":9080,"y":91553,"time":"both","level":30},{"world":"palpagos","x":11148,"y":127876,"time":"both","level":30},{"world":"palpagos","x":12537,"y":122969,"time":"both","level":30},{"world":"palpagos","x":15084,"y":89775,"time":"both","level":30},{"world":"palpagos","x":19283,"y":122512,"time":"both","level":30},{"world":"palpagos","x":23698,"y":122883,"time":"both","level":30},{"world":"palpagos","x":26222,"y":100537,"time":"both","level":30},{"world":"palpagos","x":28478,"y":126193,"time":"both","level":30},{"world":"palpagos","x":29748,"y":115296,"time":"both","level":30},{"world":"palpagos","x":30707,"y":123111,"time":"both","level":30},{"world":"palpagos","x":31229,"y":106685,"time":"both","level":30},{"world":"palpagos","x":35082,"y":119994,"time":"both","level":30},{"world":"palpagos","x":36271,"y":114794,"time":"both","level":30},{"world":"palpagos","x":37295,"y":111875,"time":"both","level":30},{"world":"palpagos","x":-149050,"y":-30550,"time":"both","boss":true,"level":15}]