[{"world":"palpagos","x":-919951,"y":-389386,"time":"both","level":65},{"world":"palpagos","x":-913192,"y":-414210,"time":"both","level":65},{"world":"palpagos","x":-904934,"y":-416961,"time":"both","level":65},{"world":"palpagos","x":-899455,"y":-376411,"time":"both","level":65},{"world":"palpagos","x":-896384,"y":-381589,"time":"both","level":65},{"world":"palpagos","x":-892031,"y":-365501,"time":"both","level":65},{"world":"palpagos","x":-883319,"y":-383296,"time":"both","level":65},{"world":"palpagos","x":-876367,"y":-356690,"time":"both","level":65},{"world":"palpagos","x":-867477,"y":-372227,"time":"both","level":65},{"world":"palpagos","x":-860035,"y":-374672,"time":"both","level":65},{"world":"palpagos","x":-854479,"y":-371695,"time":"both","level":65},{"world":"palpagos","x":-828990,"y":-426196,"time":"both","level":65},{"world":"palpagos","x":-821408,"y":-430604,"time":"both","level":65},{"world":"palpagos","x":-818620,"y":-420003,"time":"both","level":65},{"world":"palpagos","x":-815289,"y":-475503,"time":"both","level":65},{"world":"palpagos","x":-811788,"y":-457161,"time":"both","level":65},{"world":"palpagos","x":-808444,"y":-414283,"time":"both","level":65},{"world":"palpagos","x":-805071,"y":-412531,"time":"both","level":65},{"world":"palpagos","x":-801218,"y":-358300,"time":"both","level":65},{"world":"palpagos","x":-800254,"y":-430172,"time":"both","level":65},{"world":"palpagos","x":-797513,"y":-423832,"time":"both","level":65},{"world":"palpagos","x":-795161,"y":-346731,"time":"both","level":65},{"world":"palpagos","x":-793933,"y":-441138,"time":"both","level":65},{"world":"palpagos","x":-792414,"y":-420115,"time":"both","level":65},{"world":"palpagos","x":-789631,"y":-460656,"time":"both","level":65},{"world":"palpagos","x":-785797,"y":-349139,"time":"both","level":65},{"world":"palpagos","x":-782563,"y":-448158,"time":"both","level":65},{"world":"palpagos","x":-780776,"y":-426218,"time":"both","level":65},{"world":"palpagos","x":-778502,"y":-387184,"time":"both","level":65},{"world":"palpagos","x":-774915,"y":-393600,"time":"both","level":65},{"world":"palpagos","x":-773848,"y":-345077,"time":"both","level":65},{"world":"palpagos","x":-770760,"y":-363694,"time":"both","level":65},{"world":"palpagos","x":-766992,"y":-393699,"time":"both","level":65},{"world":"palpagos","x":-765625,"y":-374169,"time":"both","level":65},{"world":"palpagos","x":-760452,"y":-344114,"time":"both","level":65},{"world":"palpagos","x":-757399,"y":-341859,"time":"both","level":65},{"world":"palpagos","x":-753214,"y":-332742,"time":"both","level":65},{"world":"palpagos","x":-747542,"y":-370712,"time":"both","level":65},{"world":"palpagos","x":-744786,"y":-327272,"time":"both","level":65},{"world":"palpagos","x":-740741,"y":-352432,"time":"both","level":65},{"world":"palpagos","x":-737512,"y":-349360,"time":"both","level":65},{"world":"palpagos","x":-732589,"y":-346553,"time":"both","level":65},{"world":"palpagos","x":-726483,"y":-347949,"time":"both","level":65},{"world":"palpagos","x":-317924,"y":33676,"time":"night","level":33},{"world":"palpagos","x":-309332,"y":71940,"time":"night","level":23},{"world":"palpagos","x":-304220,"y":36116,"time":"night","level":33},{"world":"palpagos","x":-287587,"y":30313,"time":"night","level":33},{"world":"palpagos","x":-235689,"y":16343,"time":"night","level":33},{"world":"palpagos","x":-230496,"y":31904,"time":"night","level":33},{"world":"palpagos","x":-224852,"y":40840,"time":"night","level":33},{"world":"palpagos","x":-219146,"y":33122,"time":"night","level":33},{"world":"palpagos","x":-119813,"y":245923,"time":"both","level":30},{"world":"palpagos","x":-105137,"y":261241,"time":"both","level":30},{"world":"palpagos","x":-94201,"y":257528,"time":"both","level":40},{"world":"palpagos","x":-83155,"y":247295,"time":"both","level":40},{"world":"palpagos","x":-76109,"y":266550,"time":"both","level":30},{"world":"palpagos","x":-50389,"y":101594,"time":"night"},{"world":"palpagos","x":-3232,"y":41868,"time":"both","level":36},{"world":"palpagos","x":3274,"y":59786,"time":"both","level":36},{"world":"palpagos","x":14409,"y":16177,"time":"both","level":36},{"world":"palpagos","x":29610,"y":14680,"time":"both","level":36},{"world":"palpagos","x":34305,"y":36642,"time":"both","level":36},{"world":"palpagos","x":41196,"y":7987,"time":"both","level":36},{"world":"palpagos","x":47650,"y":52345,"time":"both","level":36},{"world":"palpagos","x":54212,"y":677,"time":"both","level":36},{"world":"palpagos","x":61330,"y":163461,"time":"both","level":36},{"world":"palpagos","x":71649,"y":-6820,"time":"both","level":36},{"world":"palpagos","x":74870,"y":-14240,"time":"both","level":36},{"world":"palpagos","x":80428,"y":10572,"time":"both","level":42},{"world":"palpagos","x":84546,"y":-16171,"time":"both","level":36},{"world":"palpagos","x":89942,"y":-19655,"time":"both","level":36},{"world":"palpagos","x":94445,"y":-41773,"time":"both","level":36}]